pdf_yaml_bookmark/__init__.py
pdf_yaml_bookmark/bkm_to_yaml.py
pdf_yaml_bookmark/cli.py
pdf_yaml_bookmark/common.py
pdf_yaml_bookmark/run_gs.py
pdf_yaml_bookmark/yaml_to_gs.py
pdf_yaml_bookmark-0.0.4.dist-info/METADATA
pdf_yaml_bookmark-0.0.4.dist-info/WHEEL
pdf_yaml_bookmark-0.0.4.dist-info/entry_points.txt
pdf_yaml_bookmark-0.0.4.dist-info/licenses/LICENSE
pdf_yaml_bookmark-0.0.4.dist-info/RECORD
