Metadata-Version: 2.4
Name: pdf_yaml_bookmark
Version: 0.0.4
Summary: Adds bookmarks to PDF documents.
Project-URL: Homepage, https://github.com/yutayamamoto/pdf-yaml-bookmark
Project-URL: Issues, https://github.com/yutayamamoto/pdf-yaml-bookmark/issues
Author-email: Yuta Yamamoto <jichael.y.yuta1995@gmail.com>
License-Expression: MIT
License-File: LICENSE
Classifier: Operating System :: OS Independent
Classifier: Programming Language :: Python :: 3
Requires-Python: >=3.9
Requires-Dist: pyyaml
Requires-Dist: typer
Provides-Extra: dev
Requires-Dist: build; extra == 'dev'
Requires-Dist: twine; extra == 'dev'
